area/__init__.py
area/area.py
area_lib_limendra-1.0.0.dist-info/METADATA
area_lib_limendra-1.0.0.dist-info/WHEEL
area_lib_limendra-1.0.0.dist-info/top_level.txt
area_lib_limendra-1.0.0.dist-info/RECORD
