Metadata-Version: 2.1
Name: area-lib-limendra
Version: 1.0.0
Summary: A simple library to calculate areas
Author: Limendra Singh Markam
